[
  {
    "ID da Teleconsulta": "TC-001",
    "Paciente": "Maria da Silva",
    "Médico Responsável": "Dr. João Pereira",
    "Especialidade": "Cardiologia",
    "Data e Hora": "15/10/2024 14:30",
    "Status": "Concluída",
    "Anotações": "Paciente com quadro de arritmia. Sugerido exame de ECG.",
    "Telefone do Cuidador": "1198784501",
    "Telefone do Paciente": "1198784501"
  },
  {
    "ID da Teleconsulta": "TC-002",
    "Paciente": "José Santos",
    "Data de Nascimento": "22/01/2010",
    "Médico Responsável": "Dra. Ana Costa",
    "Especialidade": "Pediatria",
    "Data e Hora": "16/10/2024 10:00",
    "Status": "Agendada",
    "Anotações": "Avaliação de rotina do desenvolvimento infantil.",
    "Telefone do Cuidador": "1198784501",
    "Telefone do Paciente": "1198784501"
  },
  {
    "ID da Teleconsulta": "TC-003",
    "Paciente": "Ana Cláudia",
    "Data de Nascimento": "06/05/2006",
    "Médico Responsável": "Dr. Lucas Martins",
    "Especialidade": "Dermatologia",
    "Data e Hora": "16/10/2024 11:45",
    "Status": "Agendada",
    "Anotações": "Lesões de pele. Paciente enviará fotos antes da consulta.",
    "Telefone do Cuidador": "11987578015"
  },
  {
    "ID da Teleconsulta": "TC-004",
    "Paciente": "Pedro Oliveira",
    "Data de Nascimento": "06/05/1995",
    "Médico Responsável": "Dr. João Pereira",
    "Especialidade": "Cardiologia",
    "Data e Hora": "17/10/2024 09:00",
    "Status": "Cancelada",
    "Anotações": "Cancelamento solicitado pelo paciente por motivo de urgência.",
    "Telefone do Cuidador": "51985351478"
  },
  {
    "ID da Teleconsulta": "TC-005",
    "Paciente": "Juliana Souza",
    "Data de Nascimento": "06/08/1979",
    "Médico Responsável": "Dra. Ana Costa",
    "Especialidade": "Clínica Geral",
    "Data e Hora": "17/10/2024 15:30",
    "Status": "Em Andamento",
    "Anotações": "Primeira consulta para acompanhamento de febre."
  },
  {
    "ID da Teleconsulta": "TC-006",
    "Paciente": "Rafael Lima",
    "Data de Nascimento": "19/03/1988",
    "Médico Responsável": "Dr. Lucas Martins",
    "Especialidade": "Dermatologia",
    "Data e Hora": "18/10/2024 09:30",
    "Status": "Concluída",
    "Anotações": "Revisão de tratamento para acne. Paciente satisfeito com os resultados."
  },
  {
    "ID da Teleconsulta": "TC-007",
    "Paciente": "Carla Mendes",
    "Data de Nascimento": "10/11/1992",
    "Médico Responsável": "Dra. Ana Costa",
    "Especialidade": "Pediatria",
    "Data e Hora": "18/10/2024 14:00",
    "Status": "Agendada",
    "Anotações": "Consulta de rotina para filho de 2 anos. Dúvidas sobre vacinação.",
    "Telefone do Cuidador": "11987654321"
  },
  {
    "ID da Teleconsulta": "TC-008",
    "Paciente": "Fernanda Rios",
    "Data de Nascimento": "25/07/1975",
    "Médico Responsável": "Dr. João Pereira",
    "Especialidade": "Cardiologia",
    "Data e Hora": "19/10/2024 11:00",
    "Status": "Agendada",
    "Anotações": "Monitoramento de pressão arterial. Análise de exames recentes.",
    "Telefone do Paciente": "21998765432"
  },
  {
    "ID da Teleconsulta": "TC-009",
    "Paciente": "Ricardo Gomes",
    "Data de Nascimento": "03/02/1960",
    "Médico Responsável": "Dr. João Pereira",
    "Especialidade": "Cardiologia",
    "Data e Hora": "19/10/2024 16:30",
    "Status": "Concluída",
    "Anotações": "Check-up geral. Paciente com histórico familiar de problemas cardíacos."
  },
  {
    "ID da Teleconsulta": "TC-010",
    "Paciente": "Laura Santos",
    "Data de Nascimento": "14/09/2001",
    "Médico Responsável": "Dr. Lucas Martins",
    "Especialidade": "Dermatologia",
    "Data e Hora": "20/10/2024 10:00",
    "Status": "Em Andamento",
    "Anotações": "Consulta para avaliação de pintas e manchas na pele."
  }
]